<?xml version="1.0"?>
<?xml-stylesheet type="text/xsl" href="ShowXmlQuestions.xsl"?>
<assessmentItems>
  <assessmentItem author="rosa.arruabarrena@ehu.es" subject="Mikologia">
    <itemBody>
      <p>Zein Amanita da jangarria?</p>
    </itemBody>
    <correctResponse>
      <response>Caesarea</response>
    </correctResponse>
    <incorrectResponses>
      <response>Phalloides</response>
      <response>Muscaria</response>
      <response>Virosa</response>
    </incorrectResponses>
  </assessmentItem>
  <assessmentItem author="mafalda001@ikasle.ehu.eus" subject="GIH/ODS">
    <itemBody>
      <p>Zer informatika enpresak eskaintzen du hezkuntza, desberdintasunak arintzeko materialak eskainiz?</p>
    </itemBody>
    <correctResponse>
      <response>Google</response>
    </correctResponse>
    <incorrectResponses>
      <response>Facebook</response>
      <response>Twiter</response>
      <response>VMicrosoft</response>
    </incorrectResponses>
  </assessmentItem>
  <assessmentItem author="julenl123@ikasle.ehu.es" subject="gatos">
    <itemBody>
      <p>gato decapitado????</p>
    </itemBody>
    <correctResponse>
      <response>no</response>
    </correctResponse>
    <incorrectResponse>
      <response>si</response>
      <response>puede</response>
      <response>blob</response>
    </incorrectResponse>
  </assessmentItem>
  <assessmentItem author="julenl123@ikasle.ehu.es" subject="probatzen">
    <itemBody>
      <p>probatzenprobatzenprobatzenprobatzen</p>
    </itemBody>
    <correctResponse>
      <response>probatzen</response>
    </correctResponse>
    <incorrectResponse>
      <response>probatzen</response>
      <response>probatzen</response>
      <response>probatzen</response>
    </incorrectResponse>
  </assessmentItem>
</assessmentItems>
